setup.py
kcommonmodule/__init__.py
kcommonmodule/logger.py
kcommonmodule.egg-info/PKG-INFO
kcommonmodule.egg-info/SOURCES.txt
kcommonmodule.egg-info/dependency_links.txt
kcommonmodule.egg-info/top_level.txt