Metadata-Version: 1.0
Name: kcommonmodule
Version: 1.4
Summary: Simple python logging
Home-page: UNKNOWN
Author: zhaodianle
Author-email: zhaodl@knownsec.com
License: UNKNOWN
Platform: UNKNOWN
